README.md
setup.py
bin/percol
percol/__init__.py
percol/action.py
percol/actions.py
percol/ansi.py
percol/cli.py
percol/command.py
percol/debug.py
percol/display.py
percol/finder.py
percol/info.py
percol/key.py
percol/lazyarray.py
percol/markup.py
percol/model.py
percol/tty.py
percol/view.py
percolator.egg-info/PKG-INFO
percolator.egg-info/SOURCES.txt
percolator.egg-info/dependency_links.txt
percolator.egg-info/requires.txt
percolator.egg-info/top_level.txt